Workbook

Sheet Сводка
A1: ПТИЦЕКОМПЛЕКС «НОВА-АГРО» — СВОДКА
A2: Запорожская область · CAPEX 12 000 млн ₽ · направление агрохолдинга · ставка на бройлер + яйцо (~70% направленческого CAPEX)
A3: Цены и нормативы — актуальные опт. РФ, II кв. 2026 (консервативно)
A5: КЛЮЧЕВЫЕ ПОКАЗАТЕЛИ
A6: CAPEX, млн ₽ | B6: =Экономика!B4
A7: Мясо птицы, т/год | B7: =Продукция!G9
A8: Куриное яйцо, млн шт./год | B8: =Продукция!G13
A9: Перепелиное яйцо, млн шт./год | B9: =Продукция!G14
A10: Корма, т/год | B10: =Корма!D12
A11: Выручка (полн. мощн.), млн ₽/год | B11: =Выручка!E12
A12: OPEX (полн. мощн.), млн ₽/год | B12: =OPEX!B13
A13: EBITDA, млн ₽/год | B13: =Экономика!B7
A14: Маржа EBITDA | B14: =Экономика!B8
A15: Простая окупаемость, лет | B15: =Экономика!B14
A16: Рабочих мест, чел. | B16: 476
A17: Единовременное поголовье, гол. | B17: 2147400
A18: Птичников/модулей, шт. | B18: 118
A20: NPV @ 10%, млн ₽ | B20: =NPV-IRR!B22
A21: IRR, % | B21: =NPV-IRR!B23
A22: Финансирование | B22: лист «Финансирование»
A23: Энергетика | B23: solar 10 МВт·ч + compost 5 т/ч (= кролики); без лок. biogaz+ГПU
A24: Подробности — листы: … CAPEX, OPEX, Экономика, NPV-IRR, Финансирование, APK-100, Допущения.

Sheet Допущения
A1: ПТИЦЕКОМПЛЕКС «НОВА-АГРО» — КЛЮЧЕВЫЕ ДОПУЩЕНИЯ И ЦЕНЫ
A2: Запорожская область | CAPEX 12 000 млн ₽ | горизонт 10 лет | старт 01.09.2026 | режим ЕСХН 6%
A3: Цены — оптовые, РФ, II кв. 2026 (консервативно). Синим — вводные параметры.
A5: ЦЕНЫ РЕАЛИЗАЦИИ И КОРМА
A6: Параметр | B6: Ед. | C6: Значение | D6: Источник / комментарий
A7: Цена бройлера (тушка+разделка, халяль) | B7: ₽/кг | C7: 205 | D7: опт тушка ~200 ₽/кг + разделка; Росптицесоюз/Kommersant, июнь 2026
A8: Цена индейки (тушка+разделка) | B8: ₽/кг | C8: 360 | D8: тушка ~335, филе 485-525; meatinfo, 2026
A9: Цена утки (тушка охл.) | B9: ₽/кг | C9: 320 | D9: тушка 309-350; meatinfo, 2026
A10: Цена гуся (тушка) | B10: ₽/кг | C10: 480 | D10: тушка 500-620 (консервативно); meatinfo, 2026
A11: Цена перепела (тушка) | B11: ₽/кг | C11: 450 | D11: опт 380-430 + премиум; meatinfo, 2026
A12: Цена куриного яйца | B12: ₽/шт | C12: 7 | D12: ≈70 ₽/дес.; опт 77-85 ₽/дес. без НДС, рынок волатилен (профицит)
A13: Цена перепелиного яйца | B13: ₽/шт | C13: 3 | D13: опт 3-3,5 ₽/шт; meatinfo, 2026
A14: Себестоимость комбикорма (собств. завод) | B14: ₽/т | C14: 28000 | D14: корм птицы ~28 тыс ₽/т (2025), собств. производство холдинга
A17: МЕТОДОЛОГИЯ И ЭТАЛОН BASELINE (КРОЛИКИ)
A18: Параметр | B18: Ед. | C18: Значение | D18: Источник / комментарий
A19: Ставка дисконтирования (для NPV/IRR) | B19: % | C19: 10 | D19: docs/1.ТЭО_МОЯ МЕЧТА.docx tab#7
A20: CAPEX solar на блоке | B20: МВт·ч / млн ₽ | C20: 10 / 1180,8 | D20: tab#23; = кролики
A21: CAPEX компost помёта | B21: т/ч / млн ₽ | C21: 5 / 36 | D21: tab#23; = кролики
A22: Локальный biogaz+ГПU в блоке | B22: — | C22: нет | D22: как кролики; помёт → APK 20 МВт·ч
A23: OPEX покупное электро | B23: млн ₽/год | C23: 0 | D23: у кроликов строки нет
A24: Удобрение из органики | B24: т/год × ₽/кг | C24: 43 800 × 12 | D24: tab#4,#205; сырьё — помёт птицы
A25: ККЗ в CAPEX блока | B25: — | C25: нет | D25: корм с ККЗ холдинга ~28 000 ₽/т; у кроликов ККЗ 958,5 млн в docx
A26: Горизонт finmodel | B26: лет | C26: 10 | D26: 2026–2035, лист «Экономика»

Sheet Продукция
A1: ПОГОЛОВЬЕ, ЦИКЛЫ И ВЫХОД ПРОДУКЦИИ
A3: Вид / продукт | B3: Единоврем. поголовье, гол. | C3: Оборотов/год | D3: Голов на убой/год | E3: Жив. масса, кг | F3: Убойный выход | G3: Мясо, т/год | H3: Падёж учтён
A4: Бройлер ROSS 308 | B4: 1440000 | C4: 6.5 | D4: 9079200 | E4: 2.5 | F4: 0.75 | G4: =D4*E4*F4/1000 | H4: 3% падёж
A5: Индейка BUT Big 6 | B5: 30000 | C5: 2 | D5: 57600 | E5: 15 | F5: 0.78 | G5: =D5*E5*F5/1000 | H5: 4% падёж
A6: Утка Cherry Valley | B6: 20000 | C6: 5 | D6: 96000 | E6: 3.5 | F6: 0.75 | G6: =D6*E6*F6/1000 | H6: 4% падёж
A7: Гусь Линдовская | B7: 2400 | C7: 2 | D7: 4560 | E7: 6 | F7: 0.72 | G7: =D7*E7*F7/1000 | H7: 5% падёж
A8: Перепёл Фараон (мясо) | B8: 150000 | C8: 7 | D8: 1018500 | E8: 0.28 | F8: 0.7 | G8: =D8*E8*F8/1000 | H8: 3% падёж
A9: ИТОГО МЯСО ПТИЦЫ | G9: =SUM(G4:G8)
A11: ЯЙЦО
A12: Продукт | B12: Несушек, гол. | C12: Яиц на несушку/год | D12: — | E12: — | F12: — | G12: Яиц, млн шт./год
A13: Куриное яйцо (Hisex/Lohmann) | B13: 480000 | C13: 320 | G13: =B13*C13/1000000
A14: Перепелиное яйцо (−90%) | B14: 25000 | C14: 280 | G14: =B14*C14/1000000

Sheet Выручка
A1: ВЫРУЧКА ПРИ ПОЛНОЙ МОЩНОСТИ
A3: Направление | B3: Объём | C3: Ед. | D3: Цена, ₽/ед. | E3: Выручка, млн ₽/год | F3: Доля
A4: Бройлер (мясо) | B4: =Продукция!G4 | C4: т | D4: =Допущения!$C$7 | E4: =B4*D4*1000/1000000 | F4: =E4/Выручка!$E$13
A5: Индейка (мясо) | B5: =Продукция!G5 | C5: т | D5: =Допущения!$C$8 | E5: =B5*D5*1000/1000000 | F5: =E5/Выручка!$E$13
A6: Утка (мясо) | B6: =Продукция!G6 | C6: т | D6: =Допущения!$C$9 | E6: =B6*D6*1000/1000000 | F6: =E6/Выручка!$E$13
A7: Гусь (мясо) | B7: =Продукция!G7 | C7: т | D7: =Допущения!$C$10 | E7: =B7*D7*1000/1000000 | F7: =E7/Выручка!$E$13
A8: Перепёл (мясо) | B8: =Продукция!G8 | C8: т | D8: =Допущения!$C$11 | E8: =B8*D8*1000/1000000 | F8: =E8/Выручка!$E$13
A9: Куриное яйцо | B9: =Продукция!$G$13 | C9: млн шт | D9: =Допущения!$C$12 | E9: =B9*D9*1000000/1000000 | F9: =E9/Выручка!$E$13
A10: Перепелиное яйцо | B10: =Продукция!$G$14 | C10: млн шт | D10: =Допущения!$C$13 | E10: =B10*D10*1000000/1000000 | F10: =E10/Выручка!$E$13
A11: Побочная продукция (перьевая/кровяная мука, жир) | E11: 25 | F11: =E11/Выручка!$E$13
A12: Удобрение из помёта (43 800 т/год × 12 ₽/кг, этalon кроликов tab#205) | B12: 43800 | C12: т | D12: 12 | E12: =B12*D12*1000/1000000 | F12: =E12/Выручка!$E$13
A13: ИТОГО ВЫРУЧКА | E13: =SUM(E4:E12) | F13: =SUM(F4:F12)
E14: =(E4+E9+E10)/Выручка!$E$13
A15: Справочно: доля «бройлер + яйцо» в выручке | E15: =(E4+E9+E10)/Выручка!$E$13

Sheet Корма
A1: БАЛАНС КОМБИКОРМОВ
A2: Корм производится на комбикормовом заводе холдинга (мощность ~300 тыс. т/год). Потребность птицеводства — доля от завода.
A4: Группа | B4: Посажено/содержится, гол./год | C4: Расход корма, кг/гол. | D4: Корма, т/год | E4: % от итога
A5: Бройлер | B5: 9360000 | C5: 4.5 | D5: =B5*C5/1000 | E5: =D5/Корма!$D$12
A6: Индейка | B6: 60000 | C6: 39 | D6: =B6*C6/1000 | E6: =D6/Корма!$D$12
A7: Утка | B7: 100000 | C7: 9.8 | D7: =B7*C7/1000 | E7: =D7/Корма!$D$12
A8: Гусь | B8: 4800 | C8: 19.2 | D8: =B8*C8/1000 | E8: =D8/Корма!$D$12
A9: Перепёл мясной | B9: 1050000 | C9: 0.78 | D9: =B9*C9/1000 | E9: =D9/Корма!$D$12
A10: Куры-несушки | B10: 480000 | C10: 42 | D10: =B10*C10/1000 | E10: =D10/Корма!$D$12
A11: Перепелиные несушки | B11: 25000 | C11: 8.03 | D11: =B11*C11/1000 | E11: =D11/Корма!$D$12
A12: ИТОГО КОРМА | D12: =SUM(D5:D11)
A14: Затраты на корма, млн ₽/год | D14: =Корма!$D$12*Допущения!$C$14/1000000

Sheet CAPEX
A1: КАПИТАЛЬНЫЕ ЗАТРАТЫ (CAPEX) — 12 000 млн ₽
A3: Объект / статья | B3: Кол-во, ед. | C3: Стоимость ед., млн ₽ | D3: Сумма, млн ₽ | E3: Группа
A4: Бройлерные птичники (18 000 гол., 2 000 м²) | B4: 80 | C4: 25 | D4: =B4*C4 | E4: Бройлер+яйцо
A5: Птичники кур-несушек (80 000 гол., клеточные) | B5: 6 | C5: 60 | D5: =B5*C5 | E5: Бройлер+яйцо
A6: Цех сортировки и упаковки яйца | B6: 1 | C6: 45 | D6: =B6*C6 | E6: Бройлер+яйцо
A7: Индюшиные птичники (2 500 гол.) | B7: 12 | C7: 35 | D7: =B7*C7 | E7: Прочие виды
A8: Утиные птичники (2 000 гол.) | B8: 10 | C8: 22 | D8: =B8*C8 | E8: Прочие виды
A9: Гусиные птичники (400 гол.) | B9: 6 | C9: 15 | D9: =B9*C9 | E9: Прочие виды
A10: Перепелиные модули мясные (50 000 гол.) | B10: 3 | C10: 90 | D10: =B10*C10 | E10: Прочие виды
A11: Перепелиные несушки (25 000 гол., ½ модуля) | B11: 1 | C11: 45 | D11: =B11*C11 | E11: Прочие виды
A12: Инкубаторий (500 000 яиц/нед.) | B12: 1 | C12: 600 | D12: =B12*C12 | E12: Общая инфраструктура
A13: Убойно-перерабатывающий комплекс | B13: 1 | C13: 2600 | D13: =B13*C13 | E13: Общая инфраструктура
A14: Холодильный склад (4 000 т) | B14: 1 | C14: 800 | D14: =B14*C14 | E14: Общая инфраструктура
A15: Склады кормов и приёмка (силосы) | B15: 1 | C15: 450 | D15: =B15*C15 | E15: Общая инфраструктура
A16: Солнечные панели 10 МВт·ч (эталон кроликов, tab#23 docx) | B16: 1 | C16: 1180.8 | D16: 1180.8 | E16: Общая инфраструктура
A17: Установка компостирования помёта 5 т/ч (эталон кроликов) | B17: 1 | C17: 36 | D17: 36 | E17: Общая инфраструктура
A18: Инженерные сети, ЛЭП, подстанция | B18: 1 | C18: 750 | D18: =B17*C17 | E18: Общая инфраструктура
A19: Водоснабжение, скважины, очистные | B19: 1 | C19: 300 | D19: =B18*C18 | E19: Общая инфраструктура
A20: Дороги, благоустройство, ограждение | B20: 1 | C20: 183 | D20: =B19*C19 | E20: Общая инфраструктура
A21: Ветблок, лаборатория, АБК, противопожарная | B21: 1 | C21: 450 | D21: =B20*C20 | E21: Общая инфраструктура
A22: Родительское стадо и стартовый молодняк | B22: 1 | C22: 250 | D22: =B21*C21 | E22: Общая инфраструктура
A23: Спецтехника, SCADA, IT | B23: 1 | C23: 350 | D23: =B22*C22 | E23: Общая инфраструктура
A24: Проектирование, изыскания, пусконаладка | B24: 1 | C24: 450 | D24: =B23*C23 | E24: Общая инфраструктура
A25: Резерв (непредвиденные) | B25: 1 | C25: 33 | D25: =12000-SUM(D4:D24) | E25: Общая инфраструктура
A26: ИТОГО CAPEX | D26: =SUM(D4:D25)
A28: Бройлер+яйцо (направление) | D28: =SUMIF($E$4:$E$24,"Бройлер+яйцо",$D$4:$D$24)
A29: Прочие виды (направление) | D29: =SUMIF($E$4:$E$24,"Прочие виды",$D$4:$D$24)
A30: Общая инфраструктура | D30: =SUMIF($E$4:$E$24,"Общая инфраструктура",$D$4:$D$24)
A31: Доля «бройлер+яйцо» в направлениях (без общей инфр.) | D31: =D27/(D27+D28)

Sheet OPEX
A1: ЭКСПЛУАТАЦИОННЫЕ ЗАТРАТЫ (OPEX) ПРИ ПОЛНОЙ МОЩНОСТИ
A3: Статья затрат | B3: Сумма, млн ₽/год | C3: Доля | D3: Комментарий
A4: Корма | B4: =Корма!$D$14 | C4: =B4/OPEX!$B$13 | D4: 66,7 тыс. т × 28 000 ₽/т (собств. завод холдинга)
A5: Суточный молодняк, инкуб. яйцо, ремонт стада | B5: 280 | C5: =B5/OPEX!$B$13 | D5: закупка/воспроизводство
A6: ФОТ с отчислениями (страховые ~30%) | B6: 520 | C6: =B6/OPEX!$B$13 | D6: 480 раб. мест; см. «Штат»
A7: Ветпрепараты, вакцины, биозащита | B7: 75 | C7: =B7/OPEX!$B$13
A8: Электроэнергия (покупная) — не применяется | B8: 0 | C8: =B8/OPEX!$B$13 | D8: эталон кроликов: solar 10 МВт·ч + биogaz APK 20 МВт·ч; см. energy-budget.yaml
A9: Упаковка (мясо + яйцо) | B9: 190 | C9: =B9/OPEX!$B$13
A10: Ремонт и ТО оборудования | B10: 240 | C10: =B10/OPEX!$B$13 | D10: ~2% от CAPEX оборудования
A11: Транспорт и логистика | B11: 60 | C11: =B11/OPEX!$B$13
A12: Общехозяйственные и прочие | B12: 110 | C12: =B12/OPEX!$B$13
A13: ИТОГО OPEX | B13: =SUM(B4:B12)

Sheet Экономика
A1: ЭКОНОМИКА И ОКУПАЕМОСТЬ
A3: Показатель (полная мощность) | B3: Значение
A4: CAPEX, млн ₽ | B4: =CAPEX!$D$26
A5: Выручка, млн ₽/год | B5: =Выручка!$E$12
A6: OPEX, млн ₽/год | B6: =OPEX!$B$13
A7: EBITDA, млн ₽/год | B7: =B5-B6
A8: Маржа EBITDA | B8: =B7/B5
A9: Амортизация (10 лет, линейно), млн ₽/год | B9: =B4/10
A10: Прибыль до налога, млн ₽/год | B10: =B7-B9
A11: Налог ЕСХН 6% от прибыли, млн ₽/год | B11: =MAX(B10*0.06,0)
A12: Чистая прибыль, млн ₽/год | B12: =B10-B11
A13: Денежный поток (ЧП+аморт.), млн ₽/год | B13: =B12+B9
A14: Простая окупаемость (CAPEX/EBITDA), лет | B14: =B4/B7
A15: Окупаемость по ден. потоку, лет | B15: =B4/B13
A16: Рентабельность инвестиций (EBITDA/CAPEX) | B16: =B7/B4
A20: ВЫХОД НА МОЩНОСТЬ (10 ЛЕТ)
A21: Год | B21: 2026 | C21: 2027 | D21: 2028 | E21: 2029 | F21: 2030 | G21: 2031 | H21: 2032 | I21: 2033 | J21: 2034 | K21: 2035
A22: Загрузка мощности | B22: 0 | C22: 0.35 | D22: 0.65 | E22: 0.85 | F22: 1 | G22: 1 | H22: 1 | I22: 1 | J22: 1 | K22: 1
A23: Выручка, млн ₽ | B23: =B22*Выручка!$E$12 | C23: =C22*Выручка!$E$12 | D23: =D22*Выручка!$E$12 | E23: =E22*Выручка!$E$12 | F23: =F22*Выручка!$E$12 | G23: =G22*Выручка!$E$12 | H23: =H22*Выручка!$E$12 | I23: =I22*Выручка!$E$12 | ... K23: =K22*Выручка!$E$12
A24: EBITDA, млн ₽ | B24: =B22*$B$7 | C24: =C22*$B$7 | D24: =D22*$B$7 | E24: =E22*$B$7 | F24: =F22*$B$7 | G24: =G22*$B$7 | H24: =H22*$B$7 | I24: =I22*$B$7 | ... K24: =K22*$B$7
A25: Накопл. EBITDA − CAPEX, млн ₽ | B25: =B24-CAPEX!$D$25 | C25: =B25+C24 | D25: =C25+D24 | E25: =D25+E24 | F25: =E25+F24 | G25: =F25+G24 | H25: =G25+H24 | I25: =H25+I24 | J25: =I25+J24 | K25: =J25+K24
A26: Примечание: CAPEX/OPEX/органика синхронизированы с эталоном кроликов (energy-budget.yaml, 1.ТЭО tab#23/#205). Без локального biogaz+ГПU; без покупного электро. ЕСХН 6%.

Sheet NPV-IRR
A1: NPV / IRR — DCF @ 10% (эталон кроликов, tab#7 docx)
A2: Горизонт 2026–2035 · без долга · FCF = ЧП + амортизация · CAPEX в 2026
A3: Ставка дисконтирования | B3: =Допущения!C19 | C3: %
A5: Год | B5: Загрузка | C5: EBITDA | D5: Аморт. | E5: Прибыль до налога | F5: Налог ЕСХН 6% | G5: Чистая прибыль | H5: FCF | I5: DF @ 10% | J5: PV FCF
A6: 2026 | B6: =Экономика!B22 | C6: =Экономика!B24 | D6: =IF(B6>0,Экономика!$B$9*B6,0) | E6: =C6-D6 | F6: =MAX(E6*0.06,0) | G6: =E6-F6 | H6: =G6+D6-Экономика!$B$4 | I6: =1/(1+$B$3/100)^(6-5) | J6: =H6*I6
A7: 2027 | B7: =Экономика!C22 | C7: =Экономика!C24 | D7: =IF(B7>0,Экономика!$B$9*B7,0) | E7: =C7-D7 | F7: =MAX(E7*0.06,0) | G7: =E7-F7 | H7: =G7+D7 | I7: =1/(1+$B$3/100)^(7-5) | J7: =H7*I7
A8: 2028 | B8: =Экономика!D22 | C8: =Экономика!D24 | D8: =IF(B8>0,Экономика!$B$9*B8,0) | E8: =C8-D8 | F8: =MAX(E8*0.06,0) | G8: =E8-F8 | H8: =G8+D8 | I8: =1/(1+$B$3/100)^(8-5) | J8: =H8*I8
A9: 2029 | B9: =Экономика!E22 | C9: =Экономика!E24 | D9: =IF(B9>0,Экономика!$B$9*B9,0) | E9: =C9-D9 | F9: =MAX(E9*0.06,0) | G9: =E9-F9 | H9: =G9+D9 | I9: =1/(1+$B$3/100)^(9-5) | J9: =H9*I9
A10: 2030 | B10: =Экономика!F22 | C10: =Экономика!F24 | D10: =IF(B10>0,Экономика!$B$9*B10,0) | E10: =C10-D10 | F10: =MAX(E10*0.06,0) | G10: =E10-F10 | H10: =G10+D10 | I10: =1/(1+$B$3/100)^(10-5) | J10: =H10*I10
A11: 2031 | B11: =Экономика!G22 | C11: =Экономика!G24 | D11: =IF(B11>0,Экономика!$B$9*B11,0) | E11: =C11-D11 | F11: =MAX(E11*0.06,0) | G11: =E11-F11 | H11: =G11+D11 | I11: =1/(1+$B$3/100)^(11-5) | J11: =H11*I11
A12: 2032 | B12: =Экономика!H22 | C12: =Экономика!H24 | D12: =IF(B12>0,Экономика!$B$9*B12,0) | E12: =C12-D12 | F12: =MAX(E12*0.06,0) | G12: =E12-F12 | H12: =G12+D12 | I12: =1/(1+$B$3/100)^(12-5) | J12: =H12*I12
A13: 2033 | B13: =Экономика!I22 | C13: =Экономика!I24 | D13: =IF(B13>0,Экономика!$B$9*B13,0) | E13: =C13-D13 | F13: =MAX(E13*0.06,0) | G13: =E13-F13 | H13: =G13+D13 | I13: =1/(1+$B$3/100)^(13-5) | J13: =H13*I13
A14: 2034 | B14: =Экономика!J22 | C14: =Экономика!J24 | D14: =IF(B14>0,Экономика!$B$9*B14,0) | E14: =C14-D14 | F14: =MAX(E14*0.06,0) | G14: =E14-F14 | H14: =G14+D14 | I14: =1/(1+$B$3/100)^(14-5) | J14: =H14*I14
A15: 2035 | B15: =Экономика!K22 | C15: =Экономика!K24 | D15: =IF(B15>0,Экономика!$B$9*B15,0) | E15: =C15-D15 | F15: =MAX(E15*0.06,0) | G15: =E15-F15 | H15: =G15+D15 | I15: =1/(1+$B$3/100)^(15-5) | J15: =H15*I15
A16: 2036 | B16: =1 | C16: =Экономика!$B$7 | D16: =IF(B16>0,Экономика!$B$9*B16,0) | E16: =C16-D16 | F16: =MAX(E16*0.06,0) | G16: =E16-F16 | H16: =G16+D16 | I16: =1/(1+$B$3/100)^(16-5) | J16: =H16*I16
A17: 2037 | B17: =1 | C17: =Экономика!$B$7 | D17: =IF(B17>0,Экономика!$B$9*B17,0) | E17: =C17-D17 | F17: =MAX(E17*0.06,0) | G17: =E17-F17 | H17: =G17+D17 | I17: =1/(1+$B$3/100)^(17-5) | J17: =H17*I17
A18: 2038 | B18: =1 | C18: =Экономика!$B$7 | D18: =IF(B18>0,Экономика!$B$9*B18,0) | E18: =C18-D18 | F18: =MAX(E18*0.06,0) | G18: =E18-F18 | H18: =G18+D18 | I18: =1/(1+$B$3/100)^(18-5) | J18: =H18*I18
A19: 2039 | B19: =1 | C19: =Экономика!$B$7 | D19: =IF(B19>0,Экономика!$B$9*B19,0) | E19: =C19-D19 | F19: =MAX(E19*0.06,0) | G19: =E19-F19 | H19: =G19+D19 | I19: =1/(1+$B$3/100)^(19-5) | J19: =H19*I19
A20: 2040 | B20: =1 | C20: =Экономика!$B$7 | D20: =IF(B20>0,Экономика!$B$9*B20,0) | E20: =C20-D20 | F20: =MAX(E20*0.06,0) | G20: =E20-F20 | H20: =G20+D20 | I20: =1/(1+$B$3/100)^(20-5) | J20: =H20*I20
A21: 2041 | B21: =1 | C21: =Экономика!$B$7 | D21: =IF(B21>0,Экономика!$B$9*B21,0) | E21: =C21-D21 | F21: =MAX(E21*0.06,0) | G21: =E21-F21 | H21: =G21+D21 | I21: =1/(1+$B$3/100)^(21-5) | J21: =H21*I21
A22: NPV @ 10%, млн ₽ | B22: =SUM(J6:J21)
A23: IRR, % | B23: =IRR(H6:H21)*100
A24: PI (NPV/CAPEX + 1) | B24: =B22/Экономика!B4+1
A26: Сравнение с кроликами (docx tab#7)
A27: Кролики NPV @ 10% | B27: 2779.5
A28: Кролики IRR | B28: 0.1519
A29: Горизонт DCF | B29: 16 лет (2026–2041)

Sheet Финансирование
A1: СТРУКТУРА ФИНАНСИРОВАНИЯ — ПТИЦЕКОМПЛЕКС 12 000 млн ₽
A2: Шаблон: docs/1.2-слайд Фин модель.xlsx · встройка в 100 млрд: лист «APK-100»
A3: Сумма инвестиций | B3: 12000 | C3: млн ₽
B5: Источник | C5: Статья | D5: Сумма, млн ₽ | E5: Доля | F5: Комментарий
A6: ФНБ | B6: Фонд национального благосостояния | C6: Долевое участие в проекте | D6: 600 | E6: =D6/$B$3 | F6: ~5% конверта (аналог холдинга 100 млрд)
A7: РАЛ | B7: РосАгроЛизинг | C7: Оборудование (птичники, УПК, инкубатор, холод) | D7: 2340 | E7: =D7/$B$3 | F7: 19,5% блока — как кролики 2 147,7 / 11 041,5
A8: ФРП | B8: Фонд развития промышленности | C8: — | D8: 0 | E8: =D8/$B$3 | F8: ККЗ вне блока; корм с завода холдинга
A9: Банки | B9: Коммерческие банки | C9: СМР, здания, инженерные сети | D9: 6287 | E9: =D9/$B$3 | F9: 69,4% банковской доли (как СМР у кроликов)
A10: Банки | B10: Коммерческие банки | C10: Solar 10 МВт·ч | D10: 1180.8 | E10: =D10/$B$3 | F10: эталон кроликов tab#23
A11: Банки | B11: Коммерческие банки | C11: Комpost помёта 5 т/ч | D11: 36 | E11: =D11/$B$3 | F11: эталон кроликов tab#23
A12: Банки | B12: Коммерческие банки | C12: Проектирование, пусконаладка | D12: 27 | E12: =D12/$B$3 | F12: аналог строки «Проектирование» у кроликов
A13: Банки | B13: Коммерческие банки | C13: Родительское стадо, стартовый молодняк | D13: 463 | E13: =D13/$B$3 | F13: аналог «племенные» у кроликов
A14: Банки | B14: Коммерческие банки | C14: Оборотные средства | D14: 700 | E14: =D14/$B$3 | F14: как кролики (700 млн)
A15: Банки | B15: Коммерческие банки | C15: Резерв + прочая инфраструктура | D15: =12000-SUM(D6:D14) | E15: =D15/$B$3 | F15: баланс до 12 000 (= CAPEX)
B16: ИТОГО | D16: =SUM(D6:D15) | E16: =D16/$B$3
A17: Примечание
A18: ККЗ и биогаз APK 20 МВт·ч — на уровне холдинга, не в CAPEX/OPEX блока птицы.
A19: Детализация CAPEX — лист «CAPEX»; операционная модель — «Экономика», «NPV-IRR».

Sheet APK-100
A1: ВСТРОЙКА 12 млрд ПТИЦЫ В КОНТУР APK 100 млрд (Приложение 3Б)
A2: Baseline: docs/1.2-слайд Фин модель.xlsx · блок птицы: finmodel · apk-100bln-integration.md
A3: Земля птицы: APK 250 000 га, Запорожская обл. · слот 400 га · кадастр позже
A5: № | B5: Блок | C5: Baseline (кролики), млн ₽ | D5: С птицей, млн ₽ | E5: Δ, млн ₽ | F5: Доля в 100,9 млрд
A6: 1 | B6: Птицеводческий комплекс «Нова-Агро» (слот кроликов) | C6: 11041.5 | D6: 12000 | E6: =D6-C6 | F6: =D6/$D$11
A7: 2 | B7: Тепличный комплекс | C7: 34500 | D7: 34500 | E7: 0 | F7: =D7/$D$11
A8: 3 | B8: Животноводческая ферма (КРС/МРС) | C8: 27458.5 | D8: 27458.5 | E8: 0 | F8: =D8/$D$11
A9: 4 | B9: Рыбоводство (белуга) | C9: 9000 | D9: 9000 | E9: 0 | F9: =D9/$D$11
A10: 5 | B10: Масложировой комбинат | C10: 18000 | D10: 18000 | E10: 0 | F10: =D10/$D$11
B11: ИТОГО APK | C11: =SUM(C6:C10) | D11: =SUM(D6:D10) | E11: =D11-C11 | F11: 1
A13: Источники финансирования блока 1 (12 000)
A14: Источник | B14: млн ₽ | C14: Доля блока | D14: Ссылка
A15: ФНБ | B15: =Финансирование!D6 | C15: =Финансирование!E6 | D15: лист Финансирование
A16: РАЛ | B16: =Финансирование!D7 | C16: =Финансирование!E7
A17: ФРП | B17: =Финансирование!D8 | C17: =Финансирование!E8 | D17: ККЗ вне блока
A18: Банки | B18: =SUM(Финансирование!D9:D15) | C18: =B18/12000
A19: Итого блок 1 | B19: =SUM(B15:B18) | C19: 1
A21: Общая инфра APK (без изменений)
A22: ККЗ 300 тыс. т/год | B22: корм птицы ~22% мощности
A23: Биogaz APK 20 МВт·ч | B23: помёт птицы → установка холдинга
A24: Solar 50 МВт·ч | B24: 10 МВт·ч на блоке птицы (CAPEX 12 млрд)
A26: Сценарий C: итог ровно 100 000
A27: Птица / кролики (блок 1) | B27: 12000
A28: Теплицы | B28: 34128.3
A29: Животноводство | B29: 27162.6
A30: Рыба | B30: 8903
A31: Масложир | B31: 17806.1
A32: ИТОГО | B32: 100000

Sheet Чувствительность
A1: АНАЛИЗ ЧУВСТВИТЕЛЬНОСТИ — полная мощность
A2: NPV/IRR: DCF 16 лет @10%, как лист NPV-IRR · расчёт scripts/calc-poultry-scenarios.py
A4: Сценарий | B4: Выручка | C4: OPEX | D4: EBITDA | E4: Маржа % | F4: PB лет | G4: NPV @10% | H4: IRR % | I4: Комментарий
A5: База (II кв. 2026) | B5: 5559.16 | C5: 3342.93 | D5: 2216.23 | E5: 0.399 | F5: 5.41 | G5: 2253.2 | H5: 0.1282
A6: Яйцо −15% | B6: 5397.88 | C6: 3342.93 | D6: 2054.95 | E6: 0.381 | F6: 5.84 | G6: 1250.6 | H6: 0.116 | I6: 153,6 млн шт × 5,95 ₽
A7: Яйцо −30% | B7: 5236.6 | C7: 3342.93 | D7: 1893.67 | E7: 0.362 | F7: 6.34 | G7: 248 | H7: 0.1032 | I7: профицит рынка
A8: Корм +15% | B8: 5559.16 | C8: 3623.12 | D8: 1936.04 | E8: 0.348 | F8: 6.2 | G8: 511.4 | H8: 0.1066 | I8: 28 000 → 32 200 ₽/т
A9: Корм +20% | B9: 5559.16 | C9: 3716.52 | D9: 1842.64 | E9: 0.331 | F9: 6.51 | G9: -69.2 | H9: 0.0991 | I9: стресс сырья
A10: Бройлер −10% | B10: 5210.17 | C10: 3342.93 | D10: 1867.24 | E10: 0.358 | F10: 6.43 | G10: 83.7 | H10: 0.1011 | I10: 205 → 184,5 ₽/кг
A11: Ramp 85% (как 2029) | B11: 4725.29 | C11: 2941.78 | D11: 1783.51 | E11: 0.377 | F11: 6.73 | G11: -436.8 | H11: 0.0942 | I11: выручка ×0,85; OPEX ×0,88 (часть постоянных)
A12: Комбинированный стресс | B12: 5173.88 | C12: 3623.12 | D12: 1550.76 | E12: 0.3 | F12: 7.74 | G12: -1883.7 | H12: 0.0741 | I12: яйцо −20%, бройлер −5%, корм +15%
A13: Оптимист (+5% цены мясо+яйцо) | B13: 5808.53 | C13: 3342.93 | D13: 2465.6 | E13: 0.424 | F13: 4.87 | G13: 3803.4 | H13: 0.1463

Sheet Экспорт
A1: ЭКСПОРТ — Tab#5 baseline на блок 1
A2: Птица: 0% export (finmodel 5 559 РФ). APK 10 208 млн — consolidated, вне NPV 12 млрд
A4: Сценарий | B4: Экспорт, млн ₽ | C4: Выручка finmodel | D4: EBITDA | E4: NPV @10% | F4: IRR % | G4: Примечание
A5: Птица: весь сбыт РФ (finmodel) | B5: 0 | C5: 5559.2 | D5: 2216.2 | E5: 2253.2 | F5: 0.1282 | G5: мясо, яйцо, удобрение — 0% export
A6: APK Tab#5: Натуральная кожа (КРС+МРС) | B6: 1478.5 | G6: consolidated APK; не в NPV finmodel 12 млрд
A7: APK Tab#5: Желатин халяльный | B7: 3840 | G7: consolidated APK; не в NPV finmodel 12 млрд
A8: APK Tab#5: Шерсть овец | B8: 90 | G8: consolidated APK; не в NPV finmodel 12 млрд
A9: APK Tab#5: Чёрная икра белуги | B9: 4800 | G9: consolidated APK; не в NPV finmodel 12 млрд
A10: ИТОГО APK экспорт (блок 1) | B10: 10208.5 | G10: 10 208 млн ≈ 10,2 млрд; export-apk-baseline-tab5.md
